README.md
setup.py
appyweather/__init__.py
appyweather/appyweather.py
appyweather.egg-info/PKG-INFO
appyweather.egg-info/SOURCES.txt
appyweather.egg-info/dependency_links.txt
appyweather.egg-info/requires.txt
appyweather.egg-info/top_level.txt